downloader_app/__init__.py
downloader_app/celeryapp.py
downloader_app/celeryconfig.py
downloader_app/run_downloader_tasks.py
downloader_app/settings.py
downloader_app/shapefile_module.py
downloader_app/tasks.py
downloader_app/tiff_downloader.py
downloader_app/utils.py
downloader_app-1.0.0.dist-info/LICENSE
downloader_app-1.0.0.dist-info/WHEEL
downloader_app-1.0.0.dist-info/METADATA
downloader_app-1.0.0.dist-info/RECORD
